jupyterlab_pioneer/__init__.py
jupyterlab_pioneer/_version.py
jupyterlab_pioneer/application.py
jupyterlab_pioneer/default_exporters.py
jupyterlab_pioneer/handlers.py
jupyterlab_pioneer-1.7.1.data/data/etc/jupyter/jupyter_server_config.d/jupyterlab_pioneer.json
jupyterlab_pioneer-1.7.1.data/data/share/jupyter/labextensions/jupyterlab-pioneer/package.json
jupyterlab_pioneer-1.7.1.data/data/share/jupyter/labextensions/jupyterlab-pioneer/static/256.e97fd83e4fd5003b31ca.js
jupyterlab_pioneer-1.7.1.data/data/share/jupyter/labextensions/jupyterlab-pioneer/static/747.a5f5b3cd27c485bf58cf.js
jupyterlab_pioneer-1.7.1.data/data/share/jupyter/labextensions/jupyterlab-pioneer/static/remoteEntry.c25b6dc64bfaacfe87e0.js
jupyterlab_pioneer-1.7.1.data/data/share/jupyter/labextensions/jupyterlab-pioneer/static/style.js
jupyterlab_pioneer-1.7.1.data/data/share/jupyter/labextensions/jupyterlab-pioneer/static/third-party-licenses.json
jupyterlab_pioneer-1.7.1.data/data/share/jupyter/labextensions/jupyterlab-pioneer/install.json
jupyterlab_pioneer-1.7.1.dist-info/METADATA
jupyterlab_pioneer-1.7.1.dist-info/WHEEL
jupyterlab_pioneer-1.7.1.dist-info/licenses/LICENSE
jupyterlab_pioneer-1.7.1.dist-info/RECORD
